at_hkust/__init__.py
at_hkust/auth.py
at_hkust/fbs.py
at_hkust/main.py
at_hkust/setup.py
at_hkust/ui.py
fbs_autobook_at_hkust-1.0.4.dist-info/entry_points.txt
fbs_autobook_at_hkust-1.0.4.dist-info/METADATA
fbs_autobook_at_hkust-1.0.4.dist-info/WHEEL
fbs_autobook_at_hkust-1.0.4.dist-info/RECORD
